{"tasks":[{"id":"c3fd6357-457f-4109-8c74-1ef66b19e15a","created_at":"2023-07-14T09:08:26.833Z","title":"Nome da Tarefa #1","description":"descrição #1","completed_at":null,"updated_at":"2023-07-14T09:56:25.821Z"},{"id":"60f69f39-dfb3-4df6-817b-35c5c8576e56","created_at":"2023-07-14T15:59:40.571Z","title":"Task 1","description":"Description for Task 1","completed_at":null,"updated_at":"2023-07-14T15:59:40.571Z"},{"id":"2c6e91a6-6daa-4fb1-a203-354f90adb9bc","created_at":"2023-07-14T15:59:40.572Z","title":"Task 2","description":"Description for Task 2","completed_at":null,"updated_at":"2023-07-14T15:59:40.572Z"},{"id":"beeb83d5-454b-4533-b139-4b4ddcf1019e","created_at":"2023-07-14T15:59:40.572Z","title":"Task 3","description":"Description for Task 3","completed_at":null,"updated_at":"2023-07-14T15:59:40.572Z"},{"id":"30238f9e-1e3c-4b6c-b982-67f67cbbc3e2","created_at":"2023-07-14T15:59:40.573Z","title":"Task 4","description":"Description for Task 4","completed_at":null,"updated_at":"2023-07-14T15:59:40.573Z"},{"id":"b49c9cdf-318a-4102-af89-b11d086b34f7","created_at":"2023-07-14T15:59:40.573Z","title":"Task 5","description":"Description for Task 5","completed_at":null,"updated_at":"2023-07-14T15:59:40.573Z"},{"id":"a0978254-1255-4402-97b2-5bed3db25807","created_at":"2023-07-14T15:59:40.574Z","title":"Task 6","description":"Description for Task 6","completed_at":null,"updated_at":"2023-07-14T15:59:40.574Z"},{"id":"a6fb71c3-eaaf-4e73-98ed-0bb563960b03","created_at":"2023-07-14T15:59:40.575Z","title":"Task 7","description":"Description for Task 7","completed_at":null,"updated_at":"2023-07-14T15:59:40.575Z"},{"id":"11363237-668d-4ec4-8824-00b949cb5478","created_at":"2023-07-14T15:59:40.576Z","title":"Task 8","description":"Description for Task 8","completed_at":null,"updated_at":"2023-07-14T15:59:40.576Z"},{"id":"ba41d98c-7578-4b01-acee-e79266a572a2","created_at":"2023-07-14T15:59:40.577Z","title":"Task 9","description":"Description for Task 9","completed_at":null,"updated_at":"2023-07-14T15:59:40.577Z"},{"id":"d0be9234-2795-4fe0-84ec-c5d0eba8865c","created_at":"2023-07-14T15:59:40.578Z","title":"Task 10","description":"Description for Task 10","completed_at":null,"updated_at":"2023-07-14T15:59:40.578Z"},{"id":"87480cb5-5bbf-47fe-a956-ea63299aa3b2","created_at":"2023-07-14T15:59:40.579Z","title":"Task 11","description":"Description for Task 11","completed_at":null,"updated_at":"2023-07-14T15:59:40.579Z"},{"id":"6b87883f-f9c7-492d-9a88-1d60fe2849ec","created_at":"2023-07-14T15:59:40.580Z","title":"Task 12","description":"Description for Task 12","completed_at":null,"updated_at":"2023-07-14T15:59:40.580Z"},{"id":"9130d902-bbba-4540-8a8a-78a03fbab563","created_at":"2023-07-14T15:59:40.580Z","title":"Task 13","description":"Description for Task 13","completed_at":null,"updated_at":"2023-07-14T15:59:40.580Z"},{"id":"24022b1b-9099-464d-93d0-e31923dbbd6a","created_at":"2023-07-14T15:59:40.582Z","title":"Task 14","description":"Description for Task 14","completed_at":null,"updated_at":"2023-07-14T15:59:40.582Z"},{"id":"2fc58b2f-d7f4-40f6-b0b1-369306301567","created_at":"2023-07-14T15:59:40.582Z","title":"Task 15","description":"Description for Task 15","completed_at":null,"updated_at":"2023-07-14T15:59:40.582Z"},{"id":"e899233c-6196-463a-bb7f-97e6cad7e8ee","created_at":"2023-07-14T15:59:40.583Z","title":"Task 16","description":"Description for Task 16","completed_at":null,"updated_at":"2023-07-14T15:59:40.583Z"},{"id":"38bc3d47-0a5f-4d5b-80ab-a631dbb37978","created_at":"2023-07-14T15:59:40.583Z","title":"Task 17","description":"Description for Task 17","completed_at":null,"updated_at":"2023-07-14T15:59:40.583Z"},{"id":"72dafcf2-5f0a-40e2-953a-1a1bd50153c6","created_at":"2023-07-14T15:59:40.584Z","title":"Task 18","description":"Description for Task 18","completed_at":null,"updated_at":"2023-07-14T15:59:40.584Z"},{"id":"a6ebe084-2401-4549-b554-af3e5d845518","created_at":"2023-07-14T15:59:40.584Z","title":"Task 19","description":"Description for Task 19","completed_at":null,"updated_at":"2023-07-14T15:59:40.584Z"},{"id":"1b839de1-6aec-4ec2-b90e-a8d2219f8905","created_at":"2023-07-14T15:59:40.586Z","title":"Task 20","description":"Description for Task 20","completed_at":null,"updated_at":"2023-07-14T15:59:40.586Z"}]}